imgboost/__init__.py
imgboost/enhance.py
imgboost-0.1.0.dist-info/LICENSE
imgboost-0.1.0.dist-info/METADATA
imgboost-0.1.0.dist-info/WHEEL
imgboost-0.1.0.dist-info/entry_points.txt
imgboost-0.1.0.dist-info/top_level.txt
imgboost-0.1.0.dist-info/RECORD
